thonnycontrib/block_highlight/__init__.py
thonny_block_highlight-0.3.dist-info/METADATA
thonny_block_highlight-0.3.dist-info/WHEEL
thonny_block_highlight-0.3.dist-info/top_level.txt
thonny_block_highlight-0.3.dist-info/RECORD
