Metadata-Version: 2.1
Name: thonny-block-highlight
Version: 0.3
Summary: Plug-in for Thonny IDE which highlights the current code block
Home-page: https://gitlab.com/boldidea/thonny-block-highlight
Author: Ben Davis
Author-email: ben@boldidea.org
License: MIT
Download-URL: https://gitlab.com/boldidea/thonny-block-highlight/-/archive/0.1/thonny-block-highlight-0.1.zip
Keywords: IDE education programming Thonny
Platform: Windows
Platform: macOS
Platform: Linux
Classifier: Environment :: MacOS X
Classifier: Environment :: Win32 (MS Windows)
Classifier: Environment :: X11 Applications
Classifier: Intended Audience :: Developers
Classifier: Intended Audience :: Education
Classifier: Intended Audience :: End Users/Desktop
Classifier: License :: Freeware
Classifier: License :: OSI Approved :: MIT License
Classifier: Natural Language :: English
Classifier: Operating System :: MacOS
Classifier: Operating System :: Microsoft :: Windows
Classifier: Operating System :: POSIX
Classifier: Operating System :: POSIX :: Linux
Classifier: Programming Language :: Python
Classifier: Programming Language :: Python :: 3
Classifier: Programming Language :: Python :: 3 :: Only
Classifier: Programming Language :: Python :: 3.5
Classifier: Programming Language :: Python :: 3.6
Classifier: Programming Language :: Python :: 3.7
Classifier: Topic :: Education
Classifier: Topic :: Software Development
Classifier: Topic :: Software Development :: Embedded Systems
Requires-Python: >=3.6
Requires-Dist: thonny (>=3.0.0)
